cykdl/__init__.py
cykdl/__main__.py
ykdl/__init__.py
ykdl/common.py
ykdl/compact.py
ykdl/extractor.py
ykdl/mediainfo.py
ykdl/version.py
ykdl/extractors/__init__.py
ykdl/extractors/_byted.py
ykdl/extractors/_byted_acrawler.js
ykdl/extractors/_common.py
ykdl/extractors/baomihua.py
ykdl/extractors/cctv.py
ykdl/extractors/fun.py
ykdl/extractors/generalembed.py
ykdl/extractors/generalsimple.py
ykdl/extractors/heibaizhibo.m.js
ykdl/extractors/heibaizhibo.py
ykdl/extractors/iqilu.py
ykdl/extractors/ixigua.py
ykdl/extractors/joy.py
ykdl/extractors/kankanews.py
ykdl/extractors/ku6.py
ykdl/extractors/kuwo.py
ykdl/extractors/laifeng.py
ykdl/extractors/le.py
ykdl/extractors/lizhi.py
ykdl/extractors/longzhu.py
ykdl/extractors/mgtv.py
ykdl/extractors/miaopai.py
ykdl/extractors/pps.py
ykdl/extractors/pptv.py
ykdl/extractors/singlemultimedia.py
ykdl/extractors/tudou.py
ykdl/extractors/weibo.py
ykdl/extractors/yinyuetai.py
ykdl/extractors/yizhibo.py
ykdl/extractors/youku.py
ykdl/extractors/youkujs.py
ykdl/extractors/zhangyu.py
ykdl/extractors/zhanqi.py
ykdl/extractors/zhuafan.py
ykdl/extractors/acfun/__init__.py
ykdl/extractors/acfun/acbase.py
ykdl/extractors/acfun/bangumi.py
ykdl/extractors/acfun/live.py
ykdl/extractors/acfun/video.py
ykdl/extractors/baidu/__init__.py
ykdl/extractors/baidu/music.py
ykdl/extractors/bilibili/__init__.py
ykdl/extractors/bilibili/bangumi.py
ykdl/extractors/bilibili/bilibase.py
ykdl/extractors/bilibili/idconvertor.py
ykdl/extractors/bilibili/live.py
ykdl/extractors/bilibili/util.py
ykdl/extractors/bilibili/vc.py
ykdl/extractors/bilibili/video.py
ykdl/extractors/douban/__init__.py
ykdl/extractors/douban/movie.py
ykdl/extractors/douban/music.py
ykdl/extractors/douyin/__init__.py
ykdl/extractors/douyin/live.py
ykdl/extractors/douyin/video.py
ykdl/extractors/douyu/__init__.py
ykdl/extractors/douyu/crypto-js-md5.min.js
ykdl/extractors/douyu/live.py
ykdl/extractors/douyu/util.py
ykdl/extractors/douyu/video.py
ykdl/extractors/huajiao/__init__.py
ykdl-1.8.2.dist-info/LICENSE.txt
ykdl-1.8.2.dist-info/METADATA
ykdl-1.8.2.dist-info/WHEEL
ykdl-1.8.2.dist-info/entry_points.txt
ykdl-1.8.2.dist-info/top_level.txt
ykdl-1.8.2.dist-info/zip-safe
ykdl-1.8.2.dist-info/RECORD
