Metadata-Version: 2.1
Name: ykdl
Version: 1.8.2
Summary: a video downloader written in Python
Home-page: https://github.com/SeaHOH/ykdl
Author: Zhang Ning
Author-email: zhangn1985@gmail.com
Maintainer: SeaHOH
Maintainer-email: seahoh@gmail.com
License: MIT
Keywords: video download youku acfun bilibili
Platform: any
Classifier: Development Status :: 4 - Beta
Classifier: Environment :: Console
Classifier: Intended Audience :: Developers
Classifier: Intended Audience :: End Users/Desktop
Classifier: License :: OSI Approved :: MIT License
Classifier: Operating System :: OS Independent
Classifier: Programming Language :: Python
Classifier: Programming Language :: Python :: 3
Classifier: Programming Language :: Python :: 3.5
Classifier: Programming Language :: Python :: 3.6
Classifier: Programming Language :: Python :: 3.7
Classifier: Programming Language :: Python :: 3.8
Classifier: Programming Language :: Python :: 3.9
Classifier: Programming Language :: Python :: 3.10
Classifier: Topic :: Internet
Classifier: Topic :: Internet :: WWW/HTTP
Classifier: Topic :: Multimedia
Classifier: Topic :: Multimedia :: Sound/Audio
Classifier: Topic :: Multimedia :: Video
Classifier: Topic :: Utilities
Requires-Python: >=3.5
License-File: LICENSE.txt
Requires-Dist: m3u8 (>=1.0.0)
Requires-Dist: jsengine (>=1.0.5)
Requires-Dist: colorama ; os_name == "nt"
Provides-Extra: all
Requires-Dist: quickjs ; extra == 'all'
Requires-Dist: BrotliCFFI ; extra == 'all'
Requires-Dist: ExtProxy ; extra == 'all'
Provides-Extra: br
Requires-Dist: BrotliCFFI ; extra == 'br'
Provides-Extra: js
Requires-Dist: quickjs ; extra == 'js'
Provides-Extra: net
Requires-Dist: ExtProxy ; extra == 'net'
Requires-Dist: BrotliCFFI ; extra == 'net'
Provides-Extra: proxy
Requires-Dist: ExtProxy ; extra == 'proxy'
